{"users":[{"id":3,"username":"asampal","name":"Adrian Sampaleanu","avatar_template":"/user_avatar/forum.rebol.info/asampal/{size}/3_2.png"},{"id":5,"username":"hostilefork","name":"Hostile Fork","avatar_template":"/user_avatar/forum.rebol.info/hostilefork/{size}/26_2.png"},{"id":2,"username":"iArnold","name":"Arnold","avatar_template":"/user_avatar/forum.rebol.info/iarnold/{size}/226_2.png"},{"id":14,"username":"IngoHohmann","name":"Ingo Hohmann","avatar_template":"/user_avatar/forum.rebol.info/ingohohmann/{size}/195_2.png"},{"id":4,"username":"rgchris","name":"Chris","avatar_template":"/user_avatar/forum.rebol.info/rgchris/{size}/14_2.png"},{"id":22,"username":"BlackATTR","name":"Black Attr","avatar_template":"/user_avatar/forum.rebol.info/blackattr/{size}/204_2.png"},{"id":15,"username":"rebolek","name":"","avatar_template":"/user_avatar/forum.rebol.info/rebolek/{size}/232_2.png"},{"id":35,"username":"Mark-hi","name":"Mark Hi","avatar_template":"/user_avatar/forum.rebol.info/mark-hi/{size}/212_2.png"}],"primary_groups":[],"topic_list":{"can_create_topic":false,"more_topics_url":"/c/development/8?page=1","draft":null,"draft_key":"new_topic","draft_sequence":null,"per_page":30,"topics":[{"id":21,"title":"About the Development category","fancy_title":"About the Development category","slug":"about-the-development-category","posts_count":1,"reply_count":0,"highest_post_number":1,"image_url":null,"created_at":"2017-05-18T04:47:02.285Z","last_posted_at":null,"bumped":true,"bumped_at":"2017-05-18T05:41:01.388Z","archetype":"regular","unseen":false,"pinned":true,"unpinned":null,"excerpt":"Discussion of the development of Rebol itself: language design, implementation and standard library.","visible":true,"closed":false,"archived":false,"bookmarked":null,"liked":null,"tags":[],"views":442,"like_count":0,"has_summary":false,"last_poster_username":"asampal","category_id":8,"pinned_globally":false,"featured_link":null,"posters":[{"extras":"latest single","description":"Original Poster, Most Recent Poster","user_id":3,"primary_group_id":null}]},{"id":1300,"title":"The TYPESET! representation problem","fancy_title":"The TYPESET! representation problem","slug":"the-typeset-representation-problem","posts_count":5,"reply_count":2,"highest_post_number":5,"image_url":null,"created_at":"2020-07-09T18:56:10.847Z","last_posted_at":"2022-08-28T22:34:22.526Z","bumped":true,"bumped_at":"2022-08-28T22:34:22.526Z","archetype":"regular","unseen":false,"pinned":false,"unpinned":null,"visible":true,"closed":false,"archived":false,"bookmarked":null,"liked":null,"tags":[],"views":259,"like_count":2,"has_summary":false,"last_poster_username":"hostilefork","category_id":45,"pinned_globally":false,"featured_link":null,"posters":[{"extras":"latest","description":"Original Poster, Most Recent Poster","user_id":5,"primary_group_id":null},{"extras":null,"description":"Frequent Poster","user_id":2,"primary_group_id":null}]},{"id":1944,"title":"Thinking About Isotopes Logically: ~true~ and ~false~","fancy_title":"Thinking About Isotopes Logically: ~true~ and ~false~","slug":"thinking-about-isotopes-logically-true-and-false","posts_count":2,"reply_count":0,"highest_post_number":2,"image_url":null,"created_at":"2022-08-25T23:34:33.326Z","last_posted_at":"2022-08-28T11:42:15.051Z","bumped":true,"bumped_at":"2022-08-28T17:27:54.695Z","archetype":"regular","unseen":false,"pinned":false,"unpinned":null,"visible":true,"closed":false,"archived":false,"bookmarked":null,"liked":null,"tags":[],"views":27,"like_count":2,"has_summary":false,"last_poster_username":"hostilefork","category_id":45,"pinned_globally":false,"featured_link":null,"posters":[{"extras":"latest single","description":"Original Poster, Most Recent Poster","user_id":5,"primary_group_id":null}]},{"id":1946,"title":"Better Answers than TRY and OPT For BLANK! <=> NULL","fancy_title":"Better Answers than TRY and OPT For BLANK! &lt;=&gt; NULL","slug":"better-answers-than-try-and-opt-for-blank-null","posts_count":1,"reply_count":0,"highest_post_number":1,"image_url":null,"created_at":"2022-08-28T16:39:55.626Z","last_posted_at":"2022-08-28T16:39:55.713Z","bumped":true,"bumped_at":"2022-08-28T16:50:43.231Z","archetype":"regular","unseen":false,"pinned":false,"unpinned":null,"visible":true,"closed":false,"archived":false,"bookmarked":null,"liked":null,"tags":[],"views":7,"like_count":2,"has_summary":false,"last_poster_username":"hostilefork","category_id":32,"pinned_globally":false,"featured_link":null,"posters":[{"extras":"latest single","description":"Original Poster, Most Recent Poster","user_id":5,"primary_group_id":null}]},{"id":1412,"title":"Default Values And MAKE FRAME!","fancy_title":"Default Values And MAKE FRAME!","slug":"default-values-and-make-frame","posts_count":5,"reply_count":3,"highest_post_number":6,"image_url":null,"created_at":"2020-11-22T13:24:17.661Z","last_posted_at":"2022-08-27T11:48:26.349Z","bumped":true,"bumped_at":"2022-08-27T11:48:26.349Z","archetype":"regular","unseen":false,"pinned":false,"unpinned":null,"visible":true,"closed":false,"archived":false,"bookmarked":null,"liked":null,"tags":[],"views":263,"like_count":6,"has_summary":false,"last_poster_username":"hostilefork","category_id":9,"pinned_globally":false,"featured_link":null,"posters":[{"extras":"latest single","description":"Original Poster, Most Recent Poster","user_id":5,"primary_group_id":null}]},{"id":1919,"title":"Should SET-WORD! Disallow Isotopic Assignments?","fancy_title":"Should SET-WORD! Disallow Isotopic Assignments?","slug":"should-set-word-disallow-isotopic-assignments","posts_count":4,"reply_count":1,"highest_post_number":4,"image_url":null,"created_at":"2022-08-17T08:32:28.899Z","last_posted_at":"2022-08-27T10:30:36.907Z","bumped":true,"bumped_at":"2022-08-27T10:55:52.566Z","archetype":"regular","unseen":false,"pinned":false,"unpinned":null,"visible":true,"closed":false,"archived":false,"bookmarked":null,"liked":null,"tags":[],"views":29,"like_count":4,"has_summary":false,"last_poster_username":"hostilefork","category_id":9,"pinned_globally":false,"featured_link":null,"posters":[{"extras":"latest","description":"Original Poster, Most Recent Poster","user_id":5,"primary_group_id":null},{"extras":null,"description":"Frequent Poster","user_id":14,"primary_group_id":null}]},{"id":1183,"title":"GET-BLOCK!, GET, and REDUCE","fancy_title":"GET-BLOCK!, GET, and REDUCE","slug":"get-block-get-and-reduce","posts_count":7,"reply_count":5,"highest_post_number":8,"image_url":null,"created_at":"2019-07-22T14:26:34.758Z","last_posted_at":"2022-08-26T10:07:50.253Z","bumped":true,"bumped_at":"2022-08-26T10:07:50.253Z","archetype":"regular","unseen":false,"pinned":false,"unpinned":null,"visible":true,"closed":false,"archived":false,"bookmarked":null,"liked":null,"tags":[],"views":510,"like_count":5,"has_summary":false,"last_poster_username":"hostilefork","category_id":45,"pinned_globally":false,"featured_link":null,"posters":[{"extras":"latest single","description":"Original Poster, Most Recent Poster","user_id":5,"primary_group_id":null}]},{"id":1942,"title":"BLANK! 2022: Revisiting The Datatype","fancy_title":"BLANK! 2022: Revisiting The Datatype","slug":"blank-2022-revisiting-the-datatype","posts_count":6,"reply_count":3,"highest_post_number":6,"image_url":null,"created_at":"2022-08-25T13:50:26.287Z","last_posted_at":"2022-08-26T09:28:06.310Z","bumped":true,"bumped_at":"2022-08-26T09:34:14.993Z","archetype":"regular","unseen":false,"pinned":false,"unpinned":null,"visible":true,"closed":false,"archived":false,"bookmarked":null,"liked":null,"tags":[],"views":33,"like_count":2,"has_summary":false,"last_poster_username":"hostilefork","category_id":45,"pinned_globally":false,"featured_link":null,"posters":[{"extras":"latest","description":"Original Poster, Most Recent Poster","user_id":5,"primary_group_id":null},{"extras":null,"description":"Frequent Poster","user_id":4,"primary_group_id":null}]},{"id":1799,"title":"Conflation vs. Safety, RETURN and the Finer Points of ~null~ Isotopes","fancy_title":"Conflation vs. Safety, RETURN and the Finer Points of ~null~ Isotopes","slug":"conflation-vs-safety-return-and-the-finer-points-of-null-isotopes","posts_count":6,"reply_count":2,"highest_post_number":6,"image_url":null,"created_at":"2022-04-07T04:14:06.583Z","last_posted_at":"2022-08-25T17:36:33.301Z","bumped":true,"bumped_at":"2022-08-25T17:35:09.122Z","archetype":"regular","unseen":false,"pinned":false,"unpinned":null,"visible":true,"closed":false,"archived":false,"bookmarked":null,"liked":null,"tags":[],"views":95,"like_count":6,"has_summary":false,"last_poster_username":"hostilefork","category_id":9,"pinned_globally":false,"featured_link":null,"posters":[{"extras":"latest","description":"Original Poster, Most Recent Poster","user_id":5,"primary_group_id":null},{"extras":null,"description":"Frequent Poster","user_id":22,"primary_group_id":null},{"extras":null,"description":"Frequent Poster","user_id":14,"primary_group_id":null}]},{"id":1783,"title":"Should END-able constructs all use ^META parameters?","fancy_title":"Should END-able constructs all use ^META parameters?","slug":"should-end-able-constructs-all-use-meta-parameters","posts_count":3,"reply_count":0,"highest_post_number":3,"image_url":null,"created_at":"2022-01-21T17:01:02.953Z","last_posted_at":"2022-08-25T14:45:20.070Z","bumped":true,"bumped_at":"2022-08-25T14:45:20.070Z","archetype":"regular","unseen":false,"pinned":false,"unpinned":null,"visible":true,"closed":false,"archived":false,"bookmarked":null,"liked":null,"tags":[],"views":119,"like_count":7,"has_summary":false,"last_poster_username":"hostilefork","category_id":9,"pinned_globally":false,"featured_link":null,"posters":[{"extras":"latest single","description":"Original Poster, Most Recent Poster","user_id":5,"primary_group_id":null}]},{"id":1880,"title":"Definitional Errors as BLANK!-in-NULL-out Alternative","fancy_title":"Definitional Errors as BLANK!-in-NULL-out Alternative","slug":"definitional-errors-as-blank-in-null-out-alternative","posts_count":7,"reply_count":2,"highest_post_number":7,"image_url":null,"created_at":"2022-07-14T04:21:12.435Z","last_posted_at":"2022-08-25T12:24:29.894Z","bumped":true,"bumped_at":"2022-08-25T13:59:55.303Z","archetype":"regular","unseen":false,"pinned":false,"unpinned":null,"visible":true,"closed":false,"archived":false,"bookmarked":null,"liked":null,"tags":[],"views":53,"like_count":10,"has_summary":false,"last_poster_username":"hostilefork","category_id":54,"pinned_globally":false,"featured_link":null,"posters":[{"extras":"latest","description":"Original Poster, Most Recent Poster","user_id":5,"primary_group_id":null},{"extras":null,"description":"Frequent Poster","user_id":14,"primary_group_id":null}]},{"id":113,"title":"Why (or why not) have UNSET! in Rebol-like Languages","fancy_title":"Why (or why not) have UNSET! in Rebol-like Languages","slug":"why-or-why-not-have-unset-in-rebol-like-languages","posts_count":5,"reply_count":3,"highest_post_number":5,"image_url":null,"created_at":"2017-06-01T00:46:27.613Z","last_posted_at":"2022-08-25T11:03:41.640Z","bumped":true,"bumped_at":"2022-08-25T12:50:37.804Z","archetype":"regular","unseen":false,"pinned":false,"unpinned":null,"visible":true,"closed":false,"archived":false,"bookmarked":null,"liked":null,"tags":[],"views":992,"like_count":8,"has_summary":false,"last_poster_username":"hostilefork","category_id":45,"pinned_globally":false,"featured_link":null,"posters":[{"extras":"latest","description":"Original Poster, Most Recent Poster","user_id":5,"primary_group_id":null},{"extras":null,"description":"Frequent Poster","user_id":15,"primary_group_id":null}]},{"id":1304,"title":"How to Subvert Voidification?","fancy_title":"How to Subvert Voidification?","slug":"how-to-subvert-voidification","posts_count":3,"reply_count":1,"highest_post_number":3,"image_url":null,"created_at":"2020-07-02T23:41:55.850Z","last_posted_at":"2022-08-25T08:44:09.771Z","bumped":true,"bumped_at":"2022-08-25T08:52:43.558Z","archetype":"regular","unseen":false,"pinned":false,"unpinned":null,"visible":true,"closed":false,"archived":false,"bookmarked":null,"liked":null,"tags":[],"views":165,"like_count":2,"has_summary":false,"last_poster_username":"hostilefork","category_id":9,"pinned_globally":false,"featured_link":null,"posters":[{"extras":"latest single","description":"Original Poster, Most Recent Poster","user_id":5,"primary_group_id":null}]},{"id":1941,"title":"The ^META of NULL and VOID","fancy_title":"The ^META of NULL and VOID","slug":"the-meta-of-null-and-void","posts_count":1,"reply_count":0,"highest_post_number":1,"image_url":null,"created_at":"2022-08-18T15:23:53.850Z","last_posted_at":"2022-08-18T15:23:53.850Z","bumped":true,"bumped_at":"2022-08-25T08:39:36.933Z","archetype":"regular","unseen":false,"pinned":false,"unpinned":null,"visible":true,"closed":false,"archived":false,"bookmarked":null,"liked":null,"tags":[],"views":6,"like_count":1,"has_summary":false,"last_poster_username":"hostilefork","category_id":9,"pinned_globally":false,"featured_link":null,"posters":[{"extras":"latest single","description":"Original Poster, Most Recent Poster","user_id":5,"primary_group_id":null}]},{"id":1915,"title":"Q: Should ~ Be The Unevaluated Form of VOID ?","fancy_title":"Q: Should ~ Be The Unevaluated Form of VOID ?","slug":"q-should-be-the-unevaluated-form-of-void","posts_count":4,"reply_count":0,"highest_post_number":4,"image_url":null,"created_at":"2022-08-15T12:15:23.782Z","last_posted_at":"2022-08-25T07:26:42.942Z","bumped":true,"bumped_at":"2022-08-25T07:26:42.942Z","archetype":"regular","unseen":false,"pinned":false,"unpinned":null,"visible":true,"closed":false,"archived":false,"bookmarked":null,"liked":null,"tags":[],"views":43,"like_count":4,"has_summary":false,"last_poster_username":"hostilefork","category_id":9,"pinned_globally":false,"featured_link":null,"posters":[{"extras":"latest single","description":"Original Poster, Most Recent Poster","user_id":5,"primary_group_id":null}]},{"id":1871,"title":"Discouraging use of TRAP","fancy_title":"Discouraging use of TRAP","slug":"discouraging-use-of-trap","posts_count":3,"reply_count":0,"highest_post_number":3,"image_url":null,"created_at":"2022-07-10T16:05:31.183Z","last_posted_at":"2022-08-25T05:38:32.784Z","bumped":true,"bumped_at":"2022-08-25T06:27:16.951Z","archetype":"regular","unseen":false,"pinned":false,"unpinned":null,"visible":true,"closed":false,"archived":false,"bookmarked":null,"liked":null,"tags":[],"views":43,"like_count":6,"has_summary":false,"last_poster_username":"hostilefork","category_id":32,"pinned_globally":false,"featured_link":null,"posters":[{"extras":"latest single","description":"Original Poster, Most Recent Poster","user_id":5,"primary_group_id":null}]},{"id":1940,"title":"Incomplete TRANSCODEs: Actually an Optimization Problem","fancy_title":"Incomplete TRANSCODEs: Actually an Optimization Problem","slug":"incomplete-transcodes-actually-an-optimization-problem","posts_count":1,"reply_count":0,"highest_post_number":1,"image_url":null,"created_at":"2022-08-22T15:09:13.410Z","last_posted_at":"2022-08-22T15:09:13.562Z","bumped":true,"bumped_at":"2022-08-23T04:27:12.510Z","archetype":"regular","unseen":false,"pinned":false,"unpinned":null,"visible":true,"closed":false,"archived":false,"bookmarked":null,"liked":null,"tags":[],"views":34,"like_count":2,"has_summary":false,"last_poster_username":"hostilefork","category_id":53,"pinned_globally":false,"featured_link":null,"posters":[{"extras":"latest single","description":"Original Poster, Most Recent Poster","user_id":5,"primary_group_id":null}]},{"id":1852,"title":"FAIL vs. RETURN RAISE: The New Age of Definitional Failures!","fancy_title":"FAIL vs. RETURN RAISE: The New Age of Definitional Failures!","slug":"fail-vs-return-raise-the-new-age-of-definitional-failures","posts_count":1,"reply_count":0,"highest_post_number":1,"image_url":null,"created_at":"2022-06-28T02:17:23.751Z","last_posted_at":"2022-06-28T02:17:23.890Z","bumped":true,"bumped_at":"2022-08-22T13:10:56.452Z","archetype":"regular","unseen":false,"pinned":false,"unpinned":null,"visible":true,"closed":false,"archived":false,"bookmarked":null,"liked":null,"tags":[],"views":79,"like_count":3,"has_summary":false,"last_poster_username":"hostilefork","category_id":54,"pinned_globally":false,"featured_link":null,"posters":[{"extras":"latest single","description":"Original Poster, Most Recent Poster","user_id":5,"primary_group_id":null}]},{"id":1922,"title":"The FAIL That Wins Big: Combinator Definitional Errors","fancy_title":"The FAIL That Wins Big: Combinator Definitional Errors","slug":"the-fail-that-wins-big-combinator-definitional-errors","posts_count":1,"reply_count":0,"highest_post_number":1,"image_url":null,"created_at":"2022-08-19T02:27:10.532Z","last_posted_at":"2022-08-19T02:27:10.613Z","bumped":true,"bumped_at":"2022-08-22T13:05:25.011Z","archetype":"regular","unseen":false,"pinned":false,"unpinned":null,"visible":true,"closed":false,"archived":false,"bookmarked":null,"liked":null,"tags":[],"views":22,"like_count":3,"has_summary":false,"last_poster_username":"hostilefork","category_id":54,"pinned_globally":false,"featured_link":null,"posters":[{"extras":"latest single","description":"Original Poster, Most Recent Poster","user_id":5,"primary_group_id":null}]},{"id":1939,"title":"Optimizing TRANSCODE Usage in String/Binary PARSE","fancy_title":"Optimizing TRANSCODE Usage in String/Binary PARSE","slug":"optimizing-transcode-usage-in-string-binary-parse","posts_count":1,"reply_count":0,"highest_post_number":1,"image_url":null,"created_at":"2022-08-21T19:10:10.620Z","last_posted_at":"2022-08-21T19:10:10.706Z","bumped":true,"bumped_at":"2022-08-22T09:19:47.312Z","archetype":"regular","unseen":false,"pinned":false,"unpinned":null,"visible":true,"closed":false,"archived":false,"bookmarked":null,"liked":null,"tags":[],"views":22,"like_count":2,"has_summary":false,"last_poster_username":"hostilefork","category_id":53,"pinned_globally":false,"featured_link":null,"posters":[{"extras":"latest single","description":"Original Poster, Most Recent Poster","user_id":5,"primary_group_id":null}]},{"id":1937,"title":"Binding Issues Raised by Chris's PARSE-MACHINE","fancy_title":"Binding Issues Raised by Chris&rsquo;s PARSE-MACHINE","slug":"binding-issues-raised-by-chriss-parse-machine","posts_count":5,"reply_count":0,"highest_post_number":5,"image_url":null,"created_at":"2021-01-26T03:45:09.807Z","last_posted_at":"2021-01-29T22:47:31.173Z","bumped":true,"bumped_at":"2022-08-21T11:55:17.631Z","archetype":"regular","unseen":false,"pinned":false,"unpinned":null,"visible":true,"closed":false,"archived":false,"bookmarked":null,"liked":null,"tags":[],"views":19,"like_count":2,"has_summary":false,"last_poster_username":"rgchris","category_id":49,"pinned_globally":false,"featured_link":null,"posters":[{"extras":null,"description":"Original Poster","user_id":5,"primary_group_id":null},{"extras":"latest","description":"Most Recent Poster","user_id":4,"primary_group_id":null}]},{"id":1414,"title":"Notation for Outputs in Function Specs","fancy_title":"Notation for Outputs in Function Specs","slug":"notation-for-outputs-in-function-specs","posts_count":6,"reply_count":2,"highest_post_number":6,"image_url":null,"created_at":"2020-11-22T19:21:53.938Z","last_posted_at":"2022-08-21T11:23:19.822Z","bumped":true,"bumped_at":"2022-08-21T11:23:19.822Z","archetype":"regular","unseen":false,"pinned":false,"unpinned":null,"visible":true,"closed":false,"archived":false,"bookmarked":null,"liked":null,"tags":[],"views":155,"like_count":6,"has_summary":false,"last_poster_username":"hostilefork","category_id":59,"pinned_globally":false,"featured_link":null,"posters":[{"extras":"latest","description":"Original Poster, Most Recent Poster","user_id":5,"primary_group_id":null},{"extras":null,"description":"Frequent Poster","user_id":14,"primary_group_id":null}]},{"id":1936,"title":"Errors on \"Locked\" Binding?","fancy_title":"Errors on &ldquo;Locked&rdquo; Binding?","slug":"errors-on-locked-binding","posts_count":2,"reply_count":0,"highest_post_number":2,"image_url":null,"created_at":"2021-01-31T14:44:14.275Z","last_posted_at":"2021-02-01T05:48:21.677Z","bumped":true,"bumped_at":"2022-08-21T11:02:09.880Z","archetype":"regular","unseen":false,"pinned":false,"unpinned":null,"visible":true,"closed":false,"archived":false,"bookmarked":null,"liked":null,"tags":[],"views":9,"like_count":1,"has_summary":false,"last_poster_username":"hostilefork","category_id":49,"pinned_globally":false,"featured_link":null,"posters":[{"extras":null,"description":"Original Poster","user_id":4,"primary_group_id":null},{"extras":"latest","description":"Most Recent Poster","user_id":5,"primary_group_id":null}]},{"id":1826,"title":"undefined vs. null in JavaScript","fancy_title":"undefined vs. null in JavaScript","slug":"undefined-vs-null-in-javascript","posts_count":2,"reply_count":0,"highest_post_number":2,"image_url":null,"created_at":"2022-05-18T11:22:56.839Z","last_posted_at":"2019-09-30T14:49:19.138Z","bumped":true,"bumped_at":"2022-08-20T18:49:46.485Z","archetype":"regular","unseen":false,"pinned":false,"unpinned":null,"visible":true,"closed":false,"archived":false,"bookmarked":null,"liked":null,"tags":[],"views":41,"like_count":1,"has_summary":false,"last_poster_username":"hostilefork","category_id":42,"pinned_globally":false,"featured_link":null,"posters":[{"extras":"latest single","description":"Original Poster, Most Recent Poster","user_id":5,"primary_group_id":null}]},{"id":1929,"title":"Should RETURN be Assignable on Function Interfaces?","fancy_title":"Should RETURN be Assignable on Function Interfaces?","slug":"should-return-be-assignable-on-function-interfaces","posts_count":1,"reply_count":0,"highest_post_number":1,"image_url":null,"created_at":"2022-08-20T05:32:25.485Z","last_posted_at":"2022-08-20T05:32:25.564Z","bumped":true,"bumped_at":"2022-08-20T15:52:32.005Z","archetype":"regular","unseen":false,"pinned":false,"unpinned":null,"visible":true,"closed":false,"archived":false,"bookmarked":null,"liked":null,"tags":[],"views":24,"like_count":1,"has_summary":false,"last_poster_username":"hostilefork","category_id":59,"pinned_globally":false,"featured_link":null,"posters":[{"extras":"latest single","description":"Original Poster, Most Recent Poster","user_id":5,"primary_group_id":null}]},{"id":1002,"title":"Seeing all ACTION!s as variadic FRAME!-makers","fancy_title":"Seeing all ACTION!s as variadic FRAME!-makers","slug":"seeing-all-action-s-as-variadic-frame-makers","posts_count":2,"reply_count":0,"highest_post_number":2,"image_url":null,"created_at":"2019-01-08T09:26:32.766Z","last_posted_at":"2020-11-03T14:58:10.787Z","bumped":true,"bumped_at":"2022-08-20T11:04:05.811Z","archetype":"regular","unseen":false,"pinned":false,"unpinned":null,"visible":true,"closed":false,"archived":false,"bookmarked":null,"liked":null,"tags":[],"views":406,"like_count":1,"has_summary":false,"last_poster_username":"hostilefork","category_id":9,"pinned_globally":false,"featured_link":null,"posters":[{"extras":"latest single","description":"Original Poster, Most Recent Poster","user_id":5,"primary_group_id":null}]},{"id":1167,"title":"Idea for Naming Function Arguments Out of the Way","fancy_title":"Idea for Naming Function Arguments Out of the Way","slug":"idea-for-naming-function-arguments-out-of-the-way","posts_count":6,"reply_count":1,"highest_post_number":7,"image_url":null,"created_at":"2019-05-23T14:22:52.316Z","last_posted_at":"2022-08-16T17:08:33.680Z","bumped":true,"bumped_at":"2022-08-20T10:27:35.291Z","archetype":"regular","unseen":false,"pinned":false,"unpinned":null,"visible":true,"closed":false,"archived":false,"bookmarked":null,"liked":null,"tags":[],"views":380,"like_count":5,"has_summary":false,"last_poster_username":"hostilefork","category_id":32,"pinned_globally":false,"featured_link":null,"posters":[{"extras":"latest","description":"Original Poster, Most Recent Poster","user_id":5,"primary_group_id":null},{"extras":null,"description":"Frequent Poster","user_id":35,"primary_group_id":null},{"extras":null,"description":"Frequent Poster","user_id":14,"primary_group_id":null}]},{"id":1133,"title":"Compatibility Idea: IS and ISN'T replacing == and !==, not = and <>","fancy_title":"Compatibility Idea: IS and ISN&rsquo;T replacing == and !==, not = and &lt;&gt;","slug":"compatibility-idea-is-and-isnt-replacing-and-not-and","posts_count":7,"reply_count":4,"highest_post_number":7,"image_url":null,"created_at":"2019-03-25T21:35:58.749Z","last_posted_at":"2021-04-18T20:02:20.634Z","bumped":true,"bumped_at":"2022-08-20T10:24:23.692Z","archetype":"regular","unseen":false,"pinned":false,"unpinned":null,"visible":true,"closed":false,"archived":false,"bookmarked":null,"liked":null,"tags":[],"views":490,"like_count":4,"has_summary":false,"last_poster_username":"hostilefork","category_id":32,"pinned_globally":false,"featured_link":null,"posters":[{"extras":"latest","description":"Original Poster, Most Recent Poster","user_id":5,"primary_group_id":null},{"extras":null,"description":"Frequent Poster","user_id":14,"primary_group_id":null},{"extras":null,"description":"Frequent Poster","user_id":3,"primary_group_id":null}]},{"id":1134,"title":"The History of Multi-Return in Ren-C","fancy_title":"The History of Multi-Return in Ren-C","slug":"the-history-of-multi-return-in-ren-c","posts_count":3,"reply_count":2,"highest_post_number":9,"image_url":null,"created_at":"2019-03-28T01:56:31.352Z","last_posted_at":"2022-07-04T19:10:11.594Z","bumped":true,"bumped_at":"2022-08-20T10:06:31.983Z","archetype":"regular","unseen":false,"pinned":false,"unpinned":null,"visible":true,"closed":false,"archived":false,"bookmarked":null,"liked":null,"tags":[],"views":579,"like_count":5,"has_summary":false,"last_poster_username":"hostilefork","category_id":59,"pinned_globally":false,"featured_link":null,"posters":[{"extras":"latest single","description":"Original Poster, Most Recent Poster","user_id":5,"primary_group_id":null}]},{"id":1793,"title":"(No) Alternative Local Notation in the Func Spec Dialect","fancy_title":"(No) Alternative Local Notation in the Func Spec Dialect","slug":"no-alternative-local-notation-in-the-func-spec-dialect","posts_count":1,"reply_count":0,"highest_post_number":1,"image_url":null,"created_at":"2022-03-05T20:33:12.773Z","last_posted_at":"2022-03-05T20:33:12.870Z","bumped":true,"bumped_at":"2022-08-20T08:14:11.081Z","archetype":"regular","unseen":false,"pinned":false,"unpinned":null,"visible":true,"closed":false,"archived":false,"bookmarked":null,"liked":null,"tags":[],"views":69,"like_count":2,"has_summary":false,"last_poster_username":"hostilefork","category_id":59,"pinned_globally":false,"featured_link":null,"posters":[{"extras":"latest single","description":"Original Poster, Most Recent Poster","user_id":5,"primary_group_id":null}]}]}}